Workbook

Sheet Inputs
A1: LANDED COST & CHANNEL MARGIN MODEL
A2: Taste Hub Ltd — UK private label powders. Yellow cells are inputs; everything else calculates.
A3: ⚠ PLACEHOLDERS until MpLinn Foods returns the RFQ. Replace before relying on any output.
A5: Assumption | B5: Value | C5: Unit | D5: Note
A6: SUPPLY
A7: Powder cost, retail-ready (SKU A) | B7: 0.8 | C7: £/unit | D7: RFQ §4.2 — quote at 2k/5k/10k units
A8: Powder cost, retail-ready (SKU B) | B8: 0.8 | C8: £/unit | D8: RFQ §4.2
A9: Pouch, label & filling | B9: 0.45 | C9: £/unit | D9: Supplier offers 100g–25kg formats
A10: Sea freight LCL + clearance | B10: 0.25 | C10: £/unit | D10: India → UK, ~4–5 weeks
A11: Import duty rate | B11: 0 | C11: % | D11: CETA in force 15 Jul 2026 — MUST claim preferential origin
A12: Testing per consignment | B12: 900 | C12: £ | D12: Accredited 3rd-party: EtO, heavy metals, pesticides, mycotoxins, micro, RS%
A13: Units per consignment | B13: 6000 | C13: units | D13: 2 SKUs × 3,000
A14: PRICING
A15: Trade price to wholesaler | B15: 4.75 | C15: £/unit | D15: Ex-VAT
A16: Shop RRP | B16: 12.99 | C16: £/unit | D16: Inc. VAT if standard-rated
A17: D2C RRP | B17: 15.99 | C17: £/unit | D17: Inc. VAT if standard-rated
A18: VAT / CHANNEL
A19: VAT rate if standard-rated | B19: 0.2 | C19: % | D19: Food supplements = 20%
A20: ZERO-RATED? (1 = yes, 0 = no) | B20: 1 | C20: flag | D20: 1 = zero-rated as food. Global By Nature v HMRC [2025] TC09396. NEEDS SPECIALIST OPINION
A21: Faire commission (reorders) | B21: 0.15 | C21: % | D21: 0–10% via Faire Direct for self-introduced retailers
A22: D2C payment processing | B22: 0.025 | C22: % | D22: Shopify/Stripe
A23: D2C pick, pack & postage | B23: 2.2 | C23: £/order | D23: Assumes 1 unit per order — conservative
A24: VOLUME
A25: First run, units per SKU | B25: 3000 | C25: units | D25: RFQ: negotiate down to 2,000 at premium unit price
A26: Number of SKUs, phase 1 | B26: 2 | C26: SKUs

Sheet Landed Cost
A1: LANDED COST PER UNIT
A2: 200g retail-ready pouch, delivered to UK warehouse.
A4: Cost line | B4: SKU A — Green Banana Flour | C4: SKU B — Green Banana Powder | D4: Note
A5: Powder, retail-ready | B5: =Inputs!$B$7 | C5: =Inputs!$B$8 | D5: Supplier FOB, filled & labelled
A6: Pouch, label & filling | B6: =Inputs!$B$9 | C6: =Inputs!$B$9
A7: Sea freight + clearance | B7: =Inputs!$B$10 | C7: =Inputs!$B$10 | D7: LCL
A8: Import duty | B8: =(Inputs!$B$7+Inputs!$B$9)*Inputs!$B$11 | C8: =(Inputs!$B$8+Inputs!$B$9)*Inputs!$B$11 | D8: Zero under CETA if origin claimed
A9: Testing, amortised | B9: =Inputs!$B$12/Inputs!$B$13 | C9: =Inputs!$B$12/Inputs!$B$13 | D9: Per consignment ÷ units
A10: LANDED COST | B10: =SUM(B5:B9) | C10: =SUM(C5:C9)
A12: First-run inventory commitment
A13: Units (all SKUs) | B13: =Inputs!$B$25*Inputs!$B$26
A14: Inventory cost | B14: ='Landed Cost'!$B$10*Inputs!$B$25*Inputs!$B$26

Sheet Channel Margins
A1: CHANNEL MARGIN WATERFALL
A2: =IF(Inputs!$B$20=1,"VAT MODE: ZERO-RATED as food — no VAT deducted from consumer prices.","VAT MODE: STANDARD-RATED at 20% — VAT deducted from consumer prices.")
A3: Toggle the ZERO-RATED cell on Inputs to compare. This single switch is worth ~17% of revenue.
A5: Line | B5: Wholesale (via distributor) | C5: Faire | D5: D2C (own Shopify) | E5: Note
A6: Gross price | B6: =Inputs!$B$15 | C6: =Inputs!$B$15 | D6: =Inputs!$B$17 | E6: Wholesale ex-VAT; D2C inc. VAT if standard-rated
A7: Less VAT | B7: =0 | C7: =0 | D7: =IF(Inputs!$B$20=1,0,Inputs!$B$17-Inputs!$B$17/(1+Inputs!$B$19)) | E7: Zero if zero-rated
A8: Less commission | B8: =0 | C8: =Inputs!$B$15*Inputs!$B$21 | D8: =0 | E8: Faire ~15% reorders; 0–10% Faire Direct
A9: Less payment fees | B9: =0 | C9: =0 | D9: =IF(Inputs!$B$20=1,Inputs!$B$17,Inputs!$B$17/(1+Inputs!$B$19))*Inputs!$B$22 | E9: Shopify/Stripe
A10: Less pick/pack/post | B10: =0 | C10: =0 | D10: =Inputs!$B$23 | E10: Per order
A11: NET REVENUE | B11: =Inputs!$B$15 | C11: =Inputs!$B$15*(1-Inputs!$B$21) | D11: =IF(Inputs!$B$20=1,Inputs!$B$17,Inputs!$B$17/(1+Inputs!$B$19))-IF(Inputs!$B$20=1,Inputs!$B$17,Inputs!$B$17/(1+Inputs!$B$19))*Inputs!$B$22-Inputs!$B$23
A12: Less landed cost | B12: ='Landed Cost'!$B$10 | C12: ='Landed Cost'!$B$10 | D12: ='Landed Cost'!$B$10
A13: GROSS PROFIT / UNIT | B13: =B11-B12 | C13: =C11-C12 | D13: =D11-D12
A14: GROSS MARGIN % | B14: =IF(B11=0,0,B13/B11) | C14: =IF(C11=0,0,C13/C11) | D14: =IF(D11=0,0,D13/D11)
A16: Retail price check
A17: Shop RRP | B17: =Inputs!$B$16
A18: Implied shop margin on trade price | B18: =IF(Inputs!$B$20=1,(Inputs!$B$16-Inputs!$B$15)/Inputs!$B$16,(Inputs!$B$16/(1+Inputs!$B$19)-Inputs!$B$15)/(Inputs!$B$16/(1+Inputs!$B$19)))
A19: → Needs to clear ~35–40% for a health-food retailer to list

Sheet MOQ Scenarios
A1: MOQ SCENARIOS vs £25k BUDGET
A2: Supplier has not disclosed MOQs. Finished-goods MOQs typically run 3,000–5,000 units/SKU.
A4: Scenario | B4: Units/SKU | C4: SKUs | D4: Total units | E4: Inventory £ | F4: Non-inventory £ | G4: Total £ | H4: Within £25k?
A5: Negotiated first run | B5: 2000 | C5: 2 | D5: =B5*C5 | E5: ='Landed Cost'!$B$10*D5 | F5: 15100 | G5: =E5+F5 | H5: =IF(G5<=25000,"YES","NO — over budget")
A6: Base case | B6: 3000 | C6: 2 | D6: =B6*C6 | E6: ='Landed Cost'!$B$10*D6 | F6: 15100 | G6: =E6+F6 | H6: =IF(G6<=25000,"YES","NO — over budget")
A7: Typical supplier MOQ | B7: 5000 | C7: 2 | D7: =B7*C7 | E7: ='Landed Cost'!$B$10*D7 | F7: 15100 | G7: =E7+F7 | H7: =IF(G7<=25000,"YES","NO — over budget")
A8: Single SKU fallback | B8: 3000 | C8: 1 | D8: =B8*C8 | E8: ='Landed Cost'!$B$10*D8 | F8: 15100 | G8: =E8+F8 | H8: =IF(G8<=25000,"YES","NO — over budget")
A9: Three SKUs | B9: 3000 | C9: 3 | D9: =B9*C9 | E9: ='Landed Cost'!$B$10*D9 | F9: 15100 | G9: =E9+F9 | H9: =IF(G9<=25000,"YES","NO — over budget")
A11: Non-inventory £ = compliance, brand, testing, Shopify, trade launch, contingency (see launch-plan.md).
A12: If the supplier's MOQ forces the 5,000-unit row, cut to one SKU rather than exceed budget.

Sheet 12-Month View
A1: PHASE ONE — 12-MONTH VIEW
A2: Illustrative. Trade revenue lags listing by 6–8 weeks.
B4: M0-1 Qualify | C4: M2-3 Build | D4: M3-4 Commit | E4: M5-6 Land | F4: M6-9 Sell in | G4: M9-12 Prove | H4: Total
A5: Spend | B5: 2000 | C5: 4000 | D5: 11500 | E5: 3600 | F5: 0 | G5: 0 | H5: =SUM(B5:G5)
A6: Cumulative spend | B6: =SUM($B$5:B5) | C6: =SUM($B$5:C5) | D6: =SUM($B$5:D5) | E6: =SUM($B$5:E5) | F6: =SUM($B$5:F5) | G6: =SUM($B$5:G5)
A8: Units sold (illustrative) | B8: 0 | C8: 0 | D8: 0 | E8: 300 | F8: 2200 | G8: 1500 | H8: =SUM(B8:G8)
A9: Gross profit (wholesale rate) | B9: =B8*'Channel Margins'!$B$13 | C9: =C8*'Channel Margins'!$B$13 | D9: =D8*'Channel Margins'!$B$13 | E9: =E8*'Channel Margins'!$B$13 | F9: =F8*'Channel Margins'!$B$13 | G9: =G8*'Channel Margins'!$B$13 | H9: =SUM(B9:G9)
A11: Stock remaining | B11: =Inputs!$B$25*Inputs!$B$26-SUM($B$8:B8) | C11: =Inputs!$B$25*Inputs!$B$26-SUM($B$8:C8) | D11: =Inputs!$B$25*Inputs!$B$26-SUM($B$8:D8) | E11: =Inputs!$B$25*Inputs!$B$26-SUM($B$8:E8) | F11: =Inputs!$B$25*Inputs!$B$26-SUM($B$8:F8) | G11: =Inputs!$B$25*Inputs!$B$26-SUM($B$8:G8)
A13: Gate 4: does sell-through support a second container within 6 months of landing?
A14: Units are placeholders — replace with actual sell-in as trade accounts confirm.
